oop_di/__init__.py
oop_di/_version.py
oop_di/container.py
oop_di/container_definition.py
oop_di/definition.py
oop_di/exception.py
oop_di/service_builder.py
oop_di/types.py
oop_di/extension/__init__.py
oop_di/extension/env_extension.py
oop_di/extension/extension.py
oop_di/extension/json_extension.py
oop_di-0.6.0.dist-info/licenses/LICENSE
oop_di-0.6.0.dist-info/METADATA
oop_di-0.6.0.dist-info/WHEEL
oop_di-0.6.0.dist-info/top_level.txt
oop_di-0.6.0.dist-info/RECORD
