Metadata-Version: 2.4
Name: oop-di
Version: 0.6.0
Summary: A simple OOP Dependency injection container
Author-email: Volodymyr Chub <v@chub.com.ua>
License-Expression: MIT
Project-URL: repository, https://github.com/ChubV/oop-di/
Keywords: di,dependency injection,oop
Requires-Python: >=3.10
License-File: LICENSE
Provides-Extra: dev
Requires-Dist: basedpyright>=1.31.7; extra == "dev"
Requires-Dist: ruff; extra == "dev"
Requires-Dist: poethepoet; extra == "dev"
Requires-Dist: pytest; extra == "dev"
Requires-Dist: pytest-asyncio; extra == "dev"
Dynamic: license-file
